sacct/__init__.py
sacct/sacct.py
sacct/util.py
sacct/version.py
pandas_sacct-1.2.0.dist-info/LICENSE
pandas_sacct-1.2.0.dist-info/METADATA
pandas_sacct-1.2.0.dist-info/WHEEL
pandas_sacct-1.2.0.dist-info/top_level.txt
pandas_sacct-1.2.0.dist-info/RECORD
