Metadata-Version: 2.1
Name: pandas-sacct
Version: 1.2.0
Summary: Read Slurm sacct as pandas dataframes
Home-page: https://gitlab.com/NERSC/pandas-sacct
Author: Brandon Cook
Author-email: bgcook@lbl.gov
License: UNKNOWN
Platform: UNKNOWN
Requires-Python: >=3.6
Requires-Dist: pandas
